mdast_cli/__init__.py
mdast_cli/cr_report_generator.py
mdast_cli/mdast_scan.py
mdast_cli/distribution_systems/__init__.py
mdast_cli/distribution_systems/app_center.py
mdast_cli/distribution_systems/appgallery.py
mdast_cli/distribution_systems/appstore.py
mdast_cli/distribution_systems/firebase.py
mdast_cli/distribution_systems/google_play.py
mdast_cli/distribution_systems/nexus.py
mdast_cli/distribution_systems/nexus2.py
mdast_cli/distribution_systems/rumarket.py
mdast_cli/distribution_systems/rustore.py
mdast_cli/distribution_systems/appstore_client/__init__.py
mdast_cli/distribution_systems/appstore_client/store.py
mdast_cli/distribution_systems/appstore_client/schemas/__init__.py
mdast_cli/distribution_systems/appstore_client/schemas/store_authenticate_req.py
mdast_cli/distribution_systems/appstore_client/schemas/store_authenticate_resp.py
mdast_cli/distribution_systems/appstore_client/schemas/store_buyproduct_req.py
mdast_cli/distribution_systems/appstore_client/schemas/store_buyproduct_resp.py
mdast_cli/distribution_systems/appstore_client/schemas/store_download_req.py
mdast_cli/distribution_systems/appstore_client/schemas/store_download_resp.py
mdast_cli/distribution_systems/gpapi/__init__.py
mdast_cli/distribution_systems/gpapi/config.py
mdast_cli/distribution_systems/gpapi/device.properties
mdast_cli/distribution_systems/gpapi/googleplay.py
mdast_cli/distribution_systems/gpapi/googleplay_pb2.py
mdast_cli/distribution_systems/gpapi/utils.py
mdast_cli/helpers/__init__.py
mdast_cli/helpers/const.py
mdast_cli/helpers/helpers.py
mdast_cli_core/__init__.py
mdast_cli_core/api.py
mdast_cli_core/base.py
mdast_cli_core/token.py
mdast_cli-2025.9.0.dist-info/METADATA
mdast_cli-2025.9.0.dist-info/WHEEL
mdast_cli-2025.9.0.dist-info/entry_points.txt
mdast_cli-2025.9.0.dist-info/top_level.txt
mdast_cli-2025.9.0.dist-info/RECORD
