Metadata-Version: 2.4
Name: mdast_cli
Version: 2025.9.0
Summary: Dynamic-Mobile-Security
Home-page: https://github.com/Dynamic-Mobile-Security/mdast-cli
Author: Dynamic-Mobile-Security
Classifier: Programming Language :: Python :: 3.9
Classifier: License :: OSI Approved :: MIT License
Classifier: Operating System :: Unix
Requires-Dist: altgraph==0.17
Requires-Dist: beautifulsoup4==4.10.0
Requires-Dist: cachetools==4.1.1
Requires-Dist: certifi>=2023.7.22
Requires-Dist: cffi==1.15.0
Requires-Dist: chardet>=3.0.4
Requires-Dist: charset-normalizer==2.0.12
Requires-Dist: cryptography>=37.0.2
Requires-Dist: google==3.0.0
Requires-Dist: google-api-core==1.22.4
Requires-Dist: google-api-python-client==1.12.3
Requires-Dist: google-auth==1.22.1
Requires-Dist: google-auth-httplib2==0.0.4
Requires-Dist: googleapis-common-protos==1.52.0
Requires-Dist: httplib2==0.21.0
Requires-Dist: idna==2.10
Requires-Dist: protobuf>=4.21.6
Requires-Dist: pyasn1==0.4.8
Requires-Dist: pyasn1-modules==0.2.8
Requires-Dist: pycparser==2.21
Requires-Dist: pyparsing==3.0.7
Requires-Dist: pytz>=2021.1
Requires-Dist: requests>=2.23.0
Requires-Dist: rsa==4.8
Requires-Dist: six>=1.15.0
Requires-Dist: soupsieve==2.3.1
Requires-Dist: uritemplate==3.0.1
Requires-Dist: urllib3>=1.26.13
Dynamic: author
Dynamic: classifier
Dynamic: description
Dynamic: description-content-type
Dynamic: home-page
Dynamic: requires-dist
Dynamic: summary
